moehlenhoff_alpha2/__init__.py
moehlenhoff_alpha2-1.3.1.dist-info/LICENSE
moehlenhoff_alpha2-1.3.1.dist-info/METADATA
moehlenhoff_alpha2-1.3.1.dist-info/WHEEL
moehlenhoff_alpha2-1.3.1.dist-info/RECORD
