Metadata-Version: 2.1
Name: moehlenhoff-alpha2
Version: 1.3.1
Summary: Python client for the Moehlenhoff Alpha2 underfloor heating system
Home-page: https://github.com/j-a-n/python-moehlenhoff-alpha2
Author: Jan Schneider
Author-email: oss@janschneider.net
Requires-Python: >=3.7,<4.0
Classifier: License :: OSI Approved :: GNU General Public License v3 (GPLv3)
Classifier: Programming Language :: Python :: 3
Classifier: Programming Language :: Python :: 3.7
Classifier: Programming Language :: Python :: 3.8
Classifier: Programming Language :: Python :: 3.9
Classifier: Programming Language :: Python :: 3.10
Classifier: Programming Language :: Python :: 3.11
Classifier: Programming Language :: Python :: 3.12
Requires-Dist: aiohttp
Requires-Dist: xmltodict
Project-URL: Repository, https://github.com/j-a-n/python-moehlenhoff-alpha2
